["WANT", {"Name": "TMTanalyst", "Time": 20180604, "Text": ".@Spotify really needs a mute/block artist/song feature. There are so many artists I either hate or don\u2019t want to s\u2026 https://t.co/eYhe0ylwFM", "clean_text": "@SPOTIFY REALLY NEEDS A MUTEBLOCK ARTISTSONG FEATURE THERE ARE SO MANY ARTISTS I EITHER HATE OR DONT WANT TO S ", "count1": 0, "count2": 1, "count3": 0, "count4": 1}, {"Name": "TMTanalyst", "Time": 20180604, "Text": "Just because @Spotify doesn\u2019t want to be in a position to police artists like @rkelly , @chrisbrown @TedNugent  and\u2026 https://t.co/wCpbWYRWDB", "clean_text": "JUST BECAUSE @SPOTIFY DOESNT WANT TO BE IN A POSITION TO POLICE ARTISTS LIKE @RKELLY  @CHRISBROWN @TEDNUGENT  AND ", "count1": 0, "count2": 1, "count3": 0, "count4": 2}]