["TGT", {"Name": "CitronResearch", "Time": 20181226, "Text": "$FB Backing up the sleigh.  $160 tgt.  Citron presents the only information that counts on $FB looking past the rhe\u2026 https://t.co/CLnUVa9s4C", "clean_text": "FB BACKING SLEIGH TGT CITRON PRESENTS INFORMATION COUNTS FB PAST RHE", "count1": 1, "count2": 0, "count3": 1, "count4": 0}, {"Name": "CitronResearch", "Time": 20181220, "Text": "$TWTR has become Harvey Weinstein of social media. Price tgt $20  Amnesty Intl study cannot be ignored by Wall St.\u2026 https://t.co/YhlwBSuVrJ", "clean_text": "TWTR BECOME HARVEY WEINSTEIN SOCIAL MEDIA PRICE TGT AMNESTY INTL STUDY IGNORED WALL ST", "count1": 0, "count2": 1, "count3": 1, "count4": 0}]