["SUCH", {"Name": "UnderwaterCap", "Time": 20180406, "Text": "...I still lean towards Blockchain awaits its netscape moment. Stage is set for high-throughput infrastructure such\u2026 https://t.co/aSJZo2uc9x", "clean_text": "I STILL LEAN TOWARDS BLOCKCHAIN AWAITS ITS NETSCAPE MOMENT STAGE IS SET FOR HIGHTHROUGHPUT INFRASTRUCTURE SUCH ", "count1": 0, "count2": 0, "count3": 0, "count4": 1}, {"Name": "HedgeyeENERGY", "Time": 20180327, "Text": "@AndrewpMcLain There is such thing as TMI in IR decks...  I think that tactic is often used to distract investors a\u2026 https://t.co/Q7VxnLaPRo", "clean_text": "@ANDREWPMCLAIN THERE IS SUCH THING AS TMI IN IR DECKS  I THINK THAT TACTIC IS OFTEN USED TO DISTRACT INVESTORS A ", "count1": 0, "count2": 0, "count3": 1, "count4": 1}]