["FOXBET", {"Name": "ValueDude", "Time": 20191015, "Text": "Meadowlands (Fanduel / Pointsbet but mostly Fanduel) #1: 45% mkt share\nResorts (Draftkings / FoxBet / Resorts) #2: 30% mkt shr", "clean_text": "MEADOWLANDS FANDUEL  POINTSBET BUT MOSTLY FANDUEL #1 45% MKT SHARE\nRESORTS DRAFTKINGS  FOXBET  RESORTS #2 30% MKT SHR", "count1": 0, "count2": 0, "count3": 0, "count4": 1}, {"Name": "ValueDude", "Time": 20191015, "Text": "Still appears to be a 2-horse race with Fanduel / Draftkings with Foxbet likely making some inroads.  Monmouth (Wil\u2026 https://t.co/T711REhXtN", "clean_text": "STILL APPEARS TO BE A 2HORSE RACE WITH FANDUEL  DRAFTKINGS WITH FOXBET LIKELY MAKING SOME INROADS  MONMOUTH WIL ", "count1": 0, "count2": 0, "count3": 0, "count4": 1}]