["ANY", {"Name": "AureliusValue", "Time": 20190627, "Text": "$BANC SEC declares J. Sugarman as business partner of Galanis and \"the biggest winner from the fraud\".  Any thought\u2026 https://t.co/Q1UfSoHcrJ", "clean_text": "BANC SEC DECLARES J SUGARMAN AS BUSINESS PARTNER OF GALANIS AND THE BIGGEST WINNER FROM THE FRAUD  ANY THOUGHT ", "count1": 1, "count2": 0, "count3": 0, "count4": 1}, {"Name": "pmarca", "Time": 20190626, "Text": "RT @Golden: 2/ We are attempting to build a very versatile query tool that has capabilities we don\u2019t see in any other query tool \u2014 not just\u2026", "clean_text": "RT @GOLDEN 2 WE ARE ATTEMPTING TO BUILD A VERY VERSATILE QUERY TOOL THAT HAS CAPABILITIES WE DONT SEE IN ANY OTHER QUERY TOOL NOT JUST", "count1": 0, "count2": 1, "count3": 1, "count4": 1}]