["SOME", {"Name": "KerrisdaleCap", "Time": 20190206, "Text": "@radarcorp888 We sold some at those higher prices, and bought a lot back at lower prices in Q4 and YTD. Regardless\u2026 https://t.co/ce4fYFbRyn", "clean_text": "@RADARCORP888 WE SOLD SOME AT THOSE HIGHER PRICES AND BOUGHT A LOT BACK AT LOWER PRICES IN Q4 AND YTD REGARDLESS ", "count1": 0, "count2": 0, "count3": 0, "count4": 1}, {"Name": "ActivistShorts", "Time": 20190205, "Text": "Featuring some of the trends that defined activist shorts in 2018 and our shorts top five. https://t.co/UgqTSszEyc", "clean_text": "FEATURING SOME OF THE TRENDS THAT DEFINED ACTIVIST SHORTS IN 2018 AND OUR SHORTS TOP FIVE ", "count1": 1, "count2": 0, "count3": 0, "count4": 1}]