["LOL", {"Name": "xuexishenghuo", "Time": 20190808, "Text": "You call this non-operating expense? Lol \u201cincreased non-operating short-term expenses associated with the Company\u2019s\u2026 https://t.co/2vb14zTqPk", "clean_text": "YOU CALL THIS NONOPERATING EXPENSE LOL INCREASED NONOPERATING SHORTTERM EXPENSES ASSOCIATED WITH THE COMPANYS ", "count1": 0, "count2": 0, "count3": 0, "count4": 1}, {"Name": "MicroFundy", "Time": 20190726, "Text": "@sharkbiotech @CapitalObserver @michaelsantoli @TheStalwart lol", "clean_text": "@SHARKBIOTECH @CAPITALOBSERVER @MICHAELSANTOLI @THESTALWART LOL", "count1": 0, "count2": 0, "count3": 0, "count4": 1}]