[{"Name": "GothamResearch", "Time": "20191031", "Text": "\u201cJP Morgan Downgrades $CRTO to Underweight : PT $16.00\u201d\n\nA stone\u2019s throw from our original price target, set 2 years ago. Well done, JPM! \ud83d\udc4d"}, {"Name": "marketfolly", "Time": "20191031", "Text": "Larry Robbins\u2019 Glenview Capital trims its Brookdale Senior Living stake https://t.co/HjJG6U43HF $BKD"}, {"Name": "GrantsPub", "Time": "20191031", "Text": "Almost Daily Grant's 10/31: Knife Catchers, Inc.     https://t.co/2SGk5XqIiq https://t.co/U4kcMMbAWz"}]